<?xml version='1.0' encoding='UTF-8'?>
<opponent>
    <lastupdate>1697473915172</lastupdate>
    <enabled>false</enabled>
    <first>Yumeko</first>
    <last>Jabami</last>
    <label>Yumeko</label>
    <pic>0-select.png</pic>
    <gender>female</gender>
    <from>Kakegurui: Compulsive Gambler</from>
    <writer>coolcat001100</writer>
    <artist>coolcat001100</artist>
    <description>A strange girl with a knack for games of chance, the first and last thoughts on Yumeko's mind are always about the luck of the draw. It's not like she suffers from a gambling addiction... because she enjoys having one.</description>
    <layers>6</layers>
    <default-costume-name />
    <has_collectibles>true</has_collectibles>
    <lines>1394</lines>
    <poses>170</poses>
</opponent>
